LICENSE
MANIFEST.in
README.md
setup.py
spacings/__init__.py
spacings/moran.py
spacings/rps.py
spacings.egg-info/PKG-INFO
spacings.egg-info/SOURCES.txt
spacings.egg-info/dependency_links.txt
spacings.egg-info/not-zip-safe
spacings.egg-info/requires.txt
spacings.egg-info/top_level.txt
spacings/rps_tables/RPS_norm_edge_table_fit_spline__p_to_x.csv
spacings/rps_tables/RPS_norm_edge_table_fit_spline__x_to_p.csv
spacings/rps_tables/long_1_RPS_table_fit_Bspline_coefficients.csv
spacings/rps_tables/long_1_RPS_table_fit_Bspline_knots.csv
spacings/rps_tables/long_1_RPS_table_fit_N_values.csv
spacings/rps_tables/long_1_RPS_table_fit_p_values.csv
spacings/rps_tables/long_1_RPS_table_fit_smoothing_degree.csv
spacings/rps_tables/long_1_RPS_table_fit_x_mean.csv
spacings/rps_tables/long_1_RPS_table_fit_x_std.csv