Metadata-Version: 2.1
Name: spacings
Version: 0.0.5
Summary: Spacings
Home-page: https://github.com/philippeller/spacings
Author: Philipp Eller, Lolian Shtembari
Author-email: peller.phys@gmail.com
License: Apache 2.0
Platform: UNKNOWN
Requires-Python: >=3.6
License-File: LICENSE
